skafos/VERSION
skafos/__init__.py
skafos/exceptions.py
skafos/http.py
skafos/models.py
skafos/utilities.py
skafos-0.3.0.dist-info/LICENSE.txt
skafos-0.3.0.dist-info/METADATA
skafos-0.3.0.dist-info/WHEEL
skafos-0.3.0.dist-info/top_level.txt
skafos-0.3.0.dist-info/RECORD
