Metadata-Version: 2.1
Name: skafos
Version: 0.3.0
Summary: Python wrapper for loading, fetching, and listing model versions with the Skafos platform.
Home-page: https://github.com/skafos/skafossdk
Author: Skafos, LLC
Author-email: skafos@skafos.ai
License: Apache Software License
Project-URL: Dashboard, https://dashboard.skafos.ai
Project-URL: SDK Documentation, https://sdk.skafos.ai
Project-URL: Source, https://github.com/skafos/skafossdk
Project-URL: Website, https://skafos.ai
Keywords: machine learning delivery,mobile deployment,model versioning
Platform: UNKNOWN
Classifier: Development Status :: 4 - Beta
Classifier: Intended Audience :: Developers
Classifier: License :: OSI Approved :: Apache Software License
Classifier: Programming Language :: Python :: 3
Requires-Python: >=3
Requires-Dist: requests (==2.21.0)
